{
  "pages": [
    {
      "path": "pages/splash/splash",
      "style": {
        "navigationBarTitleText": "",
        "navigationStyle": "custom",
        "disableScroll": true
      }
    },
    {
      "path": "pages/index/index",
      "style": {
        "navigationBarTitleText": "Z-BLOG",
        "navigationBarBackgroundColor": "#2563eb",
        "navigationBarTextStyle": "white"
      }
    },
    {
      "path": "pages/detail/detail",
      "style": {
        "navigationBarTitleText": "文章详情",
        "navigationBarBackgroundColor": "#ffffff",
        "navigationBarTextStyle": "black"
      }
    },
    {
      "path": "pages/photos/photos",
      "style": {
        "navigationBarTitleText": "照片墙",
        "navigationBarBackgroundColor": "#0f172a",
        "navigationBarTextStyle": "white"
      }
    },
    {
      "path": "pages/category/category",
      "style": {
        "navigationBarTitleText": "分类",
        "navigationBarBackgroundColor": "#ffffff",
        "navigationBarTextStyle": "black"
      }
    },
    {
      "path": "pages/profile/profile",
      "style": {
        "navigationBarTitleText": "我的",
        "navigationBarBackgroundColor": "#2563eb",
        "navigationBarTextStyle": "white"
      }
    }
  ],
  "globalStyle": {
    "navigationBarTextStyle": "black",
    "navigationBarTitleText": "Z-BLOG",
    "navigationBarBackgroundColor": "#ffffff",
    "backgroundColor": "#f8fafc"
  }
}
